{
  "conditions": [
    {
      "type": "forge:not",
      "value": {
        "type": "forge:tag_empty",
        "tag": "forge:plates/uru"
      }
    },
    {
      "type": "forge:not",
      "value": {
        "type": "forge:tag_empty",
        "tag": "forge:ingots/uru"
      }
    }
  ],
  "type": "threecore:pressing",
  "result": {
    "tag": "forge:plates/uru"
  },
  "ingredient": {
    "tag": "forge:ingots/uru"
  },
  "cast": {
    "item": "threecore:plate_cast"
  },
  "experience": 0.0,
  "energy": 1000
}