{
  "type": "minecraft:block",
  "pools": [
    {
	  "name": "threecore:hydraulic_press",
      "rolls": 1,
      "entries": [
        {
          "type": "minecraft:item",
          "functions": [
            {
              "function": "minecraft:copy_name",
              "source": "block_entity"
            }
          ],
          "name": "threecore:hydraulic_press"
        }
      ],
      "conditions": [
        {
          "condition": "minecraft:survives_explosion"
        }
      ]
    }
  ]
}